pychangepoints/__init__.py
pychangepoints/algo_changepoints.py
pychangepoints/cost_function.pxd
pychangepoints/cost_function_multiple.pxd
pychangepoints/cython_pelt.cpython-39-x86_64-linux-gnu.so
pychangepoints/multiple_dim.cpython-39-x86_64-linux-gnu.so
pychangepoints/mutiple_algos.html
pychangepoints/mutiple_algos.pyx
pychangepoints/nonparametric.cpython-39-x86_64-linux-gnu.so
pychangepoints/nppelt.pyx
pychangepoints/pelt_cython.html
pychangepoints/pelt_cython.pyx
pychangepoints/utils.pxd
changepoint_cython-0.1.5.dist-info/LICENSE
changepoint_cython-0.1.5.dist-info/METADATA
changepoint_cython-0.1.5.dist-info/WHEEL
changepoint_cython-0.1.5.dist-info/RECORD
