Metadata-Version: 2.1
Name: changepoint-cython
Version: 0.1.5
Summary: A cython version of the changepoint R package
License: GNU General Public License v3.0
Author: Vianney Bruned
Requires-Python: >=3.8,<3.11
Classifier: License :: Other/Proprietary License
Classifier: Programming Language :: Python :: 3
Classifier: Programming Language :: Python :: 3.8
Classifier: Programming Language :: Python :: 3.9
Classifier: Programming Language :: Python :: 3.10
Requires-Dist: pandas (>=1.2.5,<2.0.0)
Requires-Dist: scikit-learn (>=1.2.0,<2.0.0)
